setup.py
searchMovice/__init__.py
searchMovice/movice.py
searchMovice.egg-info/PKG-INFO
searchMovice.egg-info/SOURCES.txt
searchMovice.egg-info/dependency_links.txt
searchMovice.egg-info/entry_points.txt
searchMovice.egg-info/requires.txt
searchMovice.egg-info/top_level.txt