Metadata-Version: 1.0
Name: searchMovice
Version: 0.1.7
Summary: 输入关键词搜索百度网盘中的电影资源
Home-page: https://zhuanlan.zhihu.com/passer
Author: passer
Author-email: 904727147@qq.com
License: UNKNOWN
Platform: UNKNOWN
